odoo/addons/sale_order_invoice_date/README.rst
odoo/addons/sale_order_invoice_date/__init__.py
odoo/addons/sale_order_invoice_date/__manifest__.py
odoo/addons/sale_order_invoice_date/hooks.py
odoo/addons/sale_order_invoice_date/i18n/fr.po
odoo/addons/sale_order_invoice_date/i18n/sale_order_invoice_date.pot
odoo/addons/sale_order_invoice_date/models/__init__.py
odoo/addons/sale_order_invoice_date/models/sale_order.py
odoo/addons/sale_order_invoice_date/models/sale_order_line.py
odoo/addons/sale_order_invoice_date/readme/CONTRIBUTORS.rst
odoo/addons/sale_order_invoice_date/readme/DESCRIPTION.rst
odoo/addons/sale_order_invoice_date/reports/__init__.py
odoo/addons/sale_order_invoice_date/reports/sale_report.py
odoo/addons/sale_order_invoice_date/reports/sale_report.xml
odoo/addons/sale_order_invoice_date/static/description/icon.png
odoo/addons/sale_order_invoice_date/static/description/index.html
odoo/addons/sale_order_invoice_date/tests/__init__.py
odoo/addons/sale_order_invoice_date/tests/test_sale_order_invoice_date.py
odoo14_addon_sale_order_invoice_date-14.0.1.0.1.dist-info/METADATA
odoo14_addon_sale_order_invoice_date-14.0.1.0.1.dist-info/WHEEL
odoo14_addon_sale_order_invoice_date-14.0.1.0.1.dist-info/top_level.txt
odoo14_addon_sale_order_invoice_date-14.0.1.0.1.dist-info/RECORD
